wallpaper/__init__.py
wallpaper/test__init__.py
wallpapers-0.0.1.dist-info/LICENSE.txt
wallpapers-0.0.1.dist-info/METADATA
wallpapers-0.0.1.dist-info/WHEEL
wallpapers-0.0.1.dist-info/top_level.txt
wallpapers-0.0.1.dist-info/RECORD
